certbot_dns_selectel_api_v2/__init__.py
certbot_dns_selectel_api_v2/dns_selectel_api_v2.py
certbot_dns_selectel_api_v2/exceptions.py
certbot_dns_selectel_api_v2/tests/__init__.py
certbot_dns_selectel_api_v2/tests/dns_selectel_api_v2_test.py
certbot_dns_selectel_api_v2-0.3.0.dist-info/LICENSE
certbot_dns_selectel_api_v2-0.3.0.dist-info/METADATA
certbot_dns_selectel_api_v2-0.3.0.dist-info/WHEEL
certbot_dns_selectel_api_v2-0.3.0.dist-info/entry_points.txt
certbot_dns_selectel_api_v2-0.3.0.dist-info/top_level.txt
certbot_dns_selectel_api_v2-0.3.0.dist-info/RECORD
