Metadata-Version: 2.1
Name: certbot-dns-selectel-api-v2
Version: 0.3.0
Summary: Selectel DNS Authenticator plugin for Certbot
Home-page: https://gitlab.com/alxrem/certbot-dns-selectel-api-v2
Author: Alexey Remizov
Author-email: alexey@remizov.org
License: Apache License 2.0
Classifier: Development Status :: 3 - Alpha
Classifier: Environment :: Plugins
Classifier: Intended Audience :: System Administrators
Classifier: License :: OSI Approved :: Apache Software License
Classifier: Operating System :: POSIX :: Linux
Classifier: Programming Language :: Python
Classifier: Programming Language :: Python :: 3
Classifier: Programming Language :: Python :: 3.8
Classifier: Programming Language :: Python :: 3.9
Classifier: Programming Language :: Python :: 3.10
Classifier: Programming Language :: Python :: 3.11
Classifier: Programming Language :: Python :: 3.12
Classifier: Topic :: Internet :: WWW/HTTP
Classifier: Topic :: Security
Classifier: Topic :: System :: Installation/Setup
Classifier: Topic :: System :: Networking
Classifier: Topic :: System :: Systems Administration
Classifier: Topic :: Utilities
Requires-Python: >= 3.8
License-File: LICENSE
Requires-Dist: setuptools
Requires-Dist: requests >=2.22
